paramnormal/__init__.py
paramnormal/activity.py
paramnormal/dist.py
paramnormal/utils.py
paramnormal/tests/__init__.py
paramnormal/tests/test_activity.py
paramnormal/tests/test_dist.py
paramnormal/tests/test_utils.py
paramnormal/tests/baseline_images/__init__.py
paramnormal/tests/baseline_images/test_activity/__init__.py
paramnormal/tests/baseline_images/test_activity/test_plot_cdf_basic.png
paramnormal/tests/baseline_images/test_activity/test_plot_cdf_fit.png
paramnormal/tests/baseline_images/test_activity/test_plot_cdf_xlog.png
paramnormal/tests/baseline_images/test_activity/test_plot_pdf_basic.png
paramnormal/tests/baseline_images/test_activity/test_plot_pdf_fit.png
paramnormal/tests/baseline_images/test_activity/test_plot_pdf_xlog.png
paramnormal/tests/baseline_images/test_activity/test_plot_sf_basic.png
paramnormal/tests/baseline_images/test_activity/test_plot_sf_fit.png
paramnormal/tests/baseline_images/test_activity/test_plot_sf_xlog.png
paramnormal-0.4.4.dist-info/LICENSE
paramnormal-0.4.4.dist-info/METADATA
paramnormal-0.4.4.dist-info/WHEEL
paramnormal-0.4.4.dist-info/top_level.txt
paramnormal-0.4.4.dist-info/RECORD
