Metadata-Version: 2.1
Name: paramnormal
Version: 0.4.4
Summary: paramnormal: Conventionally parameterized probability distributions
Home-page: http://phobson.github.io/paramnormal/
Download-URL: https://github.com/phobson/paramnormal/archive/master.zip
Author: Paul Hobson
Author-email: pmhobson@gmail.com
License: BSD 3-clause
Platform: Python 3.10 and later.
Classifier: Programming Language :: Python
Classifier: Operating System :: OS Independent
Classifier: License :: OSI Approved :: BSD License
Classifier: Development Status :: 5 - Production/Stable
Classifier: Intended Audience :: Science/Research
Classifier: Topic :: Scientific/Engineering :: Mathematics
Classifier: Programming Language :: Python :: 3.10
Classifier: Programming Language :: Python :: 3.11
Classifier: Programming Language :: Python :: 3.12
License-File: LICENSE
Requires-Dist: numpy
Requires-Dist: scipy
Requires-Dist: matplotlib
